tion/__init__.py
tion/tion.py
tion-1.28.dist-info/METADATA
tion-1.28.dist-info/WHEEL
tion-1.28.dist-info/top_level.txt
tion-1.28.dist-info/RECORD
