Metadata-Version: 2.1
Name: tion
Version: 1.28
Summary: Tion Magic Air API
Home-page: http://github.com/airens/tion
Author: Valeriy Chistyakov
Author-email: airens@mail.ru
License: MIT
Platform: UNKNOWN
Requires-Dist: requests
